{"120118100":{"name":"静海镇","next":0},"120118101":{"name":"唐官屯镇","next":0},"120118102":{"name":"独流镇","next":0},"120118103":{"name":"王口镇","next":0},"120118104":{"name":"台头镇","next":0},"120118105":{"name":"子牙镇","next":0},"120118106":{"name":"陈官屯镇","next":0},"120118107":{"name":"中旺镇","next":0},"120118108":{"name":"大邱庄镇","next":0},"120118109":{"name":"蔡公庄镇","next":0},"120118110":{"name":"梁头镇","next":0},"120118111":{"name":"团泊镇","next":0},"120118112":{"name":"双塘镇","next":0},"120118113":{"name":"大丰堆镇","next":0},"120118114":{"name":"沿庄镇","next":0},"120118115":{"name":"西翟庄镇","next":0},"120118200":{"name":"良王庄乡","next":0},"120118201":{"name":"杨成庄乡","next":0},"120118400":{"name":"天津静海经济开发区","next":0},"120118402":{"name":"天津子牙工业园区","next":0},"120118403":{"name":"团泊新城","next":0}}