{"140922100":{"name":"台城镇","next":0},"140922102":{"name":"耿镇镇","next":0},"140922103":{"name":"豆村镇","next":0},"140922104":{"name":"白家庄镇","next":0},"140922105":{"name":"东冶镇","next":0},"140922200":{"name":"沟南乡","next":0},"140922201":{"name":"东雷乡","next":0},"140922202":{"name":"高洪口乡","next":0},"140922203":{"name":"门限石乡","next":0},"140922204":{"name":"陈家庄乡","next":0},"140922205":{"name":"建安乡","next":0},"140922206":{"name":"神西乡","next":0},"140922207":{"name":"蒋坊乡","next":0},"140922208":{"name":"灵境乡","next":0},"140922209":{"name":"阳白乡","next":0},"140922210":{"name":"茹村乡","next":0}}