{"230111001":{"name":"兰河街道","next":0},"230111002":{"name":"呼兰街道","next":0},"230111003":{"name":"建设路街道","next":0},"230111004":{"name":"利民街道","next":0},"230111005":{"name":"学院路街道","next":0},"230111006":{"name":"腰卜街道","next":0},"230111007":{"name":"康金街道","next":0},"230111008":{"name":"双井街道","next":0},"230111009":{"name":"长岭街道","next":0},"230111010":{"name":"沈家街道","next":0},"230111105":{"name":"二八镇","next":0},"230111106":{"name":"石人镇","next":0},"230111107":{"name":"白奎镇","next":0},"230111109":{"name":"方台镇","next":0},"230111110":{"name":"莲花镇","next":0},"230111111":{"name":"大用镇","next":0},"230111114":{"name":"利业镇","next":0},"230111201":{"name":"杨林乡","next":0},"230111203":{"name":"许卜乡","next":0},"230111205":{"name":"孟家乡","next":0},"230111579":{"name":"呼兰农垦","next":0}}