{"350803001":{"name":"凤城街道","next":0},"350803101":{"name":"坎市镇","next":0},"350803102":{"name":"下洋镇","next":0},"350803103":{"name":"湖雷镇","next":0},"350803104":{"name":"高陂镇","next":0},"350803105":{"name":"抚市镇","next":0},"350803106":{"name":"湖坑镇","next":0},"350803107":{"name":"培丰镇","next":0},"350803108":{"name":"龙潭镇","next":0},"350803109":{"name":"峰市镇","next":0},"350803110":{"name":"城郊镇","next":0},"350803111":{"name":"仙师镇","next":0},"350803112":{"name":"虎岗镇","next":0},"350803201":{"name":"西溪乡","next":0},"350803202":{"name":"金砂乡","next":0},"350803204":{"name":"洪山乡","next":0},"350803205":{"name":"湖山乡","next":0},"350803206":{"name":"岐岭乡","next":0},"350803207":{"name":"古竹乡","next":0},"350803208":{"name":"堂堡乡","next":0},"350803209":{"name":"合溪乡","next":0},"350803211":{"name":"大溪乡","next":0},"350803212":{"name":"陈东乡","next":0},"350803213":{"name":"高头乡","next":0}}