{"361103001":{"name":"永丰街道","next":0},"361103002":{"name":"芦林街道","next":0},"361103003":{"name":"丰溪街道","next":0},"361103004":{"name":"下溪街道","next":0},"361103005":{"name":"大石街道","next":0},"361103101":{"name":"五都镇","next":0},"361103102":{"name":"洋口镇","next":0},"361103103":{"name":"横山镇","next":0},"361103104":{"name":"桐畈镇","next":0},"361103105":{"name":"湖丰镇","next":0},"361103106":{"name":"大南镇","next":0},"361103107":{"name":"排山镇","next":0},"361103108":{"name":"毛村镇","next":0},"361103109":{"name":"枧底镇","next":0},"361103110":{"name":"泉波镇","next":0},"361103111":{"name":"壶峤镇","next":0},"361103112":{"name":"霞峰镇","next":0},"361103114":{"name":"吴村镇","next":0},"361103115":{"name":"沙田镇","next":0},"361103116":{"name":"铜钹山镇","next":0},"361103202":{"name":"东阳乡","next":0},"361103204":{"name":"嵩峰乡","next":0},"361103206":{"name":"少阳乡","next":0},"361103500":{"name":"铜拔山垦殖场","next":0}}