{"371728001":{"name":"城关街道","next":0},"371728002":{"name":"鱼沃街道","next":0},"371728101":{"name":"东明集镇","next":0},"371728102":{"name":"刘楼镇","next":0},"371728103":{"name":"陆圈镇","next":0},"371728104":{"name":"马头镇","next":0},"371728105":{"name":"三春集镇","next":0},"371728106":{"name":"大屯镇","next":0},"371728107":{"name":"武胜桥镇","next":0},"371728108":{"name":"菜园集镇","next":0},"371728109":{"name":"沙窝镇","next":0},"371728110":{"name":"小井镇","next":0},"371728204":{"name":"长兴集乡","next":0},"371728205":{"name":"焦园乡","next":0}}