{"431022101":{"name":"白石渡镇","next":0},"431022102":{"name":"杨梅山镇","next":0},"431022103":{"name":"瑶岗仙镇","next":0},"431022104":{"name":"梅田镇","next":0},"431022106":{"name":"黄沙镇","next":0},"431022107":{"name":"迎春镇","next":0},"431022108":{"name":"一六镇","next":0},"431022109":{"name":"栗源镇","next":0},"431022110":{"name":"岩泉镇","next":0},"431022111":{"name":"玉溪镇","next":0},"431022112":{"name":"天塘镇","next":0},"431022113":{"name":"笆篱镇","next":0},"431022114":{"name":"里田镇","next":0},"431022115":{"name":"五岭镇","next":0},"431022201":{"name":"浆水乡","next":0},"431022202":{"name":"长村乡","next":0},"431022205":{"name":"莽山瑶族乡","next":0},"431022208":{"name":"关溪乡","next":0},"431022212":{"name":"赤石乡","next":0}}