{"500233001":{"name":"忠州街道","next":0},"500233002":{"name":"白公街道","next":0},"500233101":{"name":"新生镇","next":0},"500233102":{"name":"任家镇","next":0},"500233103":{"name":"乌杨镇","next":0},"500233104":{"name":"洋渡镇","next":0},"500233105":{"name":"东溪镇","next":0},"500233106":{"name":"复兴镇","next":0},"500233107":{"name":"石宝镇","next":0},"500233108":{"name":"汝溪镇","next":0},"500233109":{"name":"野鹤镇","next":0},"500233110":{"name":"官坝镇","next":0},"500233111":{"name":"石黄镇","next":0},"500233112":{"name":"马灌镇","next":0},"500233113":{"name":"金鸡镇","next":0},"500233114":{"name":"新立镇","next":0},"500233115":{"name":"双桂镇","next":0},"500233116":{"name":"拔山镇","next":0},"500233117":{"name":"花桥镇","next":0},"500233118":{"name":"永丰镇","next":0},"500233119":{"name":"三汇镇","next":0},"500233120":{"name":"白石镇","next":0},"500233122":{"name":"黄金镇","next":0},"500233201":{"name":"善广乡","next":0},"500233203":{"name":"石子乡","next":0},"500233204":{"name":"磨子土家族乡","next":0},"500233206":{"name":"涂井乡","next":0},"500233208":{"name":"金声乡","next":0},"500233210":{"name":"兴峰乡","next":0}}