{"511323101":{"name":"锦屏镇","next":0},"511323102":{"name":"巨龙镇","next":0},"511323103":{"name":"正源镇","next":0},"511323104":{"name":"龙云镇","next":0},"511323105":{"name":"金溪镇","next":0},"511323106":{"name":"徐家镇","next":0},"511323107":{"name":"河舒镇","next":0},"511323108":{"name":"利溪镇","next":0},"511323109":{"name":"龙蚕镇","next":0},"511323110":{"name":"杨家镇","next":0},"511323111":{"name":"罗家镇","next":0},"511323112":{"name":"福德镇","next":0},"511323113":{"name":"银汉镇","next":0},"511323114":{"name":"兴旺镇","next":0},"511323115":{"name":"相如镇","next":0},"511323201":{"name":"高庙乡","next":0},"511323202":{"name":"群乐乡","next":0},"511323203":{"name":"长梁乡","next":0},"511323204":{"name":"两路乡","next":0},"511323205":{"name":"睦坝乡","next":0},"511323207":{"name":"石梁乡","next":0},"511323208":{"name":"平头乡","next":0},"511323209":{"name":"鲜店乡","next":0},"511323211":{"name":"茶亭乡","next":0},"511323212":{"name":"诸家乡","next":0},"511323214":{"name":"骑龙乡","next":0},"511323215":{"name":"金甲乡","next":0},"511323217":{"name":"新园乡","next":0},"511323218":{"name":"三坝乡","next":0},"511323220":{"name":"碧溪乡","next":0},"511323221":{"name":"柳滩乡","next":0},"511323222":{"name":"石孔乡","next":0},"511323223":{"name":"开元乡","next":0},"511323225":{"name":"新河乡","next":0},"511323226":{"name":"南燕乡","next":0},"511323227":{"name":"天成乡","next":0},"511323228":{"name":"海田乡","next":0},"511323229":{"name":"济渡乡","next":0},"511323230":{"name":"凤石乡","next":0}}