{"620502001":{"name":"大城街道","next":0},"620502002":{"name":"七里墩街道","next":0},"620502003":{"name":"东关街道","next":0},"620502004":{"name":"中城街道","next":0},"620502005":{"name":"西关街道","next":0},"620502006":{"name":"石马坪街道","next":0},"620502007":{"name":"天水郡街道","next":0},"620502100":{"name":"玉泉镇","next":0},"620502101":{"name":"太京镇","next":0},"620502102":{"name":"藉口镇","next":0},"620502103":{"name":"皂郊镇","next":0},"620502104":{"name":"汪川镇","next":0},"620502105":{"name":"牡丹镇","next":0},"620502106":{"name":"关子镇","next":0},"620502107":{"name":"平南镇","next":0},"620502108":{"name":"天水镇","next":0},"620502109":{"name":"娘娘坝镇","next":0},"620502110":{"name":"中梁镇","next":0},"620502111":{"name":"杨家寺镇","next":0},"620502112":{"name":"齐寿镇","next":0},"620502113":{"name":"大门镇","next":0},"620502201":{"name":"秦岭乡","next":0},"620502204":{"name":"华歧乡","next":0}}